geoid/__init__.py
geoid/_meta.py
geoid/acs.py
geoid/aff.py
geoid/census.py
geoid/censusnames.py
geoid/civick.py
geoid/core.py
geoid/tiger.py
geoid/util.py
geoid-1.1.7.dist-info/METADATA
geoid-1.1.7.dist-info/WHEEL
geoid-1.1.7.dist-info/licenses/LICENSE
geoid-1.1.7.dist-info/RECORD
