Metadata-Version: 2.4
Name: geoid
Version: 1.1.7
Summary: Classes for working with census geoids
Author-email: Eric Busboom <eric@busboom.org>
License-File: LICENSE
Requires-Python: >=3.10
